smooth/__init__.py
smooth/_base.py
smooth/_tools.py
smooth/_utils.py
smooth/mcp/__init__.py
smooth/mcp/server.py
smooth_py-0.3.6.post0.dist-info/METADATA
smooth_py-0.3.6.post0.dist-info/WHEEL
smooth_py-0.3.6.post0.dist-info/RECORD
