Metadata-Version: 2.3
Name: smooth-py
Version: 0.3.6.post0
Summary: 
Author: Luca Pinchetti
Author-email: luca@circlemind.co
Requires-Python: >=3.10,<4.0
Classifier: Programming Language :: Python :: 3
Classifier: Programming Language :: Python :: 3.10
Classifier: Programming Language :: Python :: 3.11
Classifier: Programming Language :: Python :: 3.12
Classifier: Programming Language :: Python :: 3.13
Provides-Extra: mcp
Requires-Dist: deprecated (>=1.2.18,<2.0.0)
Requires-Dist: fastmcp (>=2.12.0,<3.0.0) ; extra == "mcp"
Requires-Dist: httpx (>=0.28.1,<0.29.0)
Requires-Dist: pydantic (>=2.11.7,<3.0.0)
Requires-Dist: requests (>=2.32.5,<3.0.0)
